[
    {
        "NumeroTreno": "WUfNprNmuF",
        "StazionePartenza": "StazionePartenza1",
        "StazioneArrivo": "StazioneArrivo1",
        "DataPartenza": "/Date(9607559000)/",
        "OraPartenza": "PT09H56M05S",
        "DataArrivo": "/Date(1314242395000)/",
        "OraArrivo": "PT17H39M43S",
        "NumeroMaxPasseggeri": 1106167401,
        "NumeroMinPasseggeri": 381147537,
        "TipoTreno": "TipoTreno1",
        "StatoTreno": "StatoTreno1",
        "BinarioPartenza": "Bina1",
        "BinarioArrivo": "Bina1",
        "Valuta": "Valu1",
        "PrezzoBase": 5074331213.254,
        "Note": "Note1",
        "CreatedBy": "CreatedBy1",
        "CreatedAt": "/Date(1366745320000)/",
        "ModifiedBy": "ModifiedBy1",
        "ModifiedAt": "/Date(918177853000)/"
    },
    {
        "NumeroTreno": "uzMsHNExkt",
        "StazionePartenza": "StazionePartenza2",
        "StazioneArrivo": "StazioneArrivo2",
        "DataPartenza": "/Date(955242854000)/",
        "OraPartenza": "PT21H47M57S",
        "DataArrivo": "/Date(792649371000)/",
        "OraArrivo": "PT12H35M06S",
        "NumeroMaxPasseggeri": 979769463,
        "NumeroMinPasseggeri": 452773133,
        "TipoTreno": "TipoTreno2",
        "StatoTreno": "StatoTreno2",
        "BinarioPartenza": "Bina2",
        "BinarioArrivo": "Bina2",
        "Valuta": "Valu2",
        "PrezzoBase": 5153426476.754,
        "Note": "Note2",
        "CreatedBy": "CreatedBy2",
        "CreatedAt": "/Date(432704220000)/",
        "ModifiedBy": "ModifiedBy2",
        "ModifiedAt": "/Date(202865132000)/"
    },
    {
        "NumeroTreno": "wRBNKPcxyh",
        "StazionePartenza": "StazionePartenza3",
        "StazioneArrivo": "StazioneArrivo3",
        "DataPartenza": "/Date(1416554169000)/",
        "OraPartenza": "PT15H57M36S",
        "DataArrivo": "/Date(1384994727000)/",
        "OraArrivo": "PT10H30M38S",
        "NumeroMaxPasseggeri": 796481559,
        "NumeroMinPasseggeri": 1263721558,
        "TipoTreno": "TipoTreno3",
        "StatoTreno": "StatoTreno3",
        "BinarioPartenza": "Bina3",
        "BinarioArrivo": "Bina3",
        "Valuta": "Valu3",
        "PrezzoBase": 6329726045.951,
        "Note": "Note3",
        "CreatedBy": "CreatedBy3",
        "CreatedAt": "/Date(736917717000)/",
        "ModifiedBy": "ModifiedBy3",
        "ModifiedAt": "/Date(877905163000)/"
    },
    {
        "NumeroTreno": "bjRGimhQyH",
        "StazionePartenza": "StazionePartenza4",
        "StazioneArrivo": "StazioneArrivo4",
        "DataPartenza": "/Date(84634691000)/",
        "OraPartenza": "PT23H09M54S",
        "DataArrivo": "/Date(694480016000)/",
        "OraArrivo": "PT06H05M49S",
        "NumeroMaxPasseggeri": 553632541,
        "NumeroMinPasseggeri": 854366580,
        "TipoTreno": "TipoTreno4",
        "StatoTreno": "StatoTreno4",
        "BinarioPartenza": "Bina4",
        "BinarioArrivo": "Bina4",
        "Valuta": "Valu4",
        "PrezzoBase": 641900461.632,
        "Note": "Note4",
        "CreatedBy": "CreatedBy4",
        "CreatedAt": "/Date(102845229000)/",
        "ModifiedBy": "ModifiedBy4",
        "ModifiedAt": "/Date(596380560000)/"
    },
    {
        "NumeroTreno": "DJPEjQVFcr",
        "StazionePartenza": "StazionePartenza5",
        "StazioneArrivo": "StazioneArrivo5",
        "DataPartenza": "/Date(1150540131000)/",
        "OraPartenza": "PT07H00M37S",
        "DataArrivo": "/Date(399346287000)/",
        "OraArrivo": "PT14H14M43S",
        "NumeroMaxPasseggeri": 1754573542,
        "NumeroMinPasseggeri": 1355685520,
        "TipoTreno": "TipoTreno5",
        "StatoTreno": "StatoTreno5",
        "BinarioPartenza": "Bina5",
        "BinarioArrivo": "Bina5",
        "Valuta": "Valu5",
        "PrezzoBase": 2287509837.187,
        "Note": "Note5",
        "CreatedBy": "CreatedBy5",
        "CreatedAt": "/Date(753408889000)/",
        "ModifiedBy": "ModifiedBy5",
        "ModifiedAt": "/Date(87702856000)/"
    },
    {
        "NumeroTreno": "GzFTfcLdsh",
        "StazionePartenza": "StazionePartenza6",
        "StazioneArrivo": "StazioneArrivo6",
        "DataPartenza": "/Date(1226034093000)/",
        "OraPartenza": "PT13H21M53S",
        "DataArrivo": "/Date(1195588699000)/",
        "OraArrivo": "PT15H29M14S",
        "NumeroMaxPasseggeri": 744585256,
        "NumeroMinPasseggeri": 971015877,
        "TipoTreno": "TipoTreno6",
        "StatoTreno": "StatoTreno6",
        "BinarioPartenza": "Bina6",
        "BinarioArrivo": "Bina6",
        "Valuta": "Valu6",
        "PrezzoBase": 1084034456.871,
        "Note": "Note6",
        "CreatedBy": "CreatedBy6",
        "CreatedAt": "/Date(755089848000)/",
        "ModifiedBy": "ModifiedBy6",
        "ModifiedAt": "/Date(889889277000)/"
    },
    {
        "NumeroTreno": "CGkXSeGViP",
        "StazionePartenza": "StazionePartenza7",
        "StazioneArrivo": "StazioneArrivo7",
        "DataPartenza": "/Date(369777180000)/",
        "OraPartenza": "PT22H54M20S",
        "DataArrivo": "/Date(570884726000)/",
        "OraArrivo": "PT12H49M32S",
        "NumeroMaxPasseggeri": 1304352885,
        "NumeroMinPasseggeri": 912525810,
        "TipoTreno": "TipoTreno7",
        "StatoTreno": "StatoTreno7",
        "BinarioPartenza": "Bina7",
        "BinarioArrivo": "Bina7",
        "Valuta": "Valu7",
        "PrezzoBase": 2888214953.709,
        "Note": "Note7",
        "CreatedBy": "CreatedBy7",
        "CreatedAt": "/Date(143707644000)/",
        "ModifiedBy": "ModifiedBy7",
        "ModifiedAt": "/Date(979467053000)/"
    },
    {
        "NumeroTreno": "GrRFeuEnUs",
        "StazionePartenza": "StazionePartenza8",
        "StazioneArrivo": "StazioneArrivo8",
        "DataPartenza": "/Date(612428224000)/",
        "OraPartenza": "PT08H57M23S",
        "DataArrivo": "/Date(338662412000)/",
        "OraArrivo": "PT18H08M54S",
        "NumeroMaxPasseggeri": 144648876,
        "NumeroMinPasseggeri": 770262676,
        "TipoTreno": "TipoTreno8",
        "StatoTreno": "StatoTreno8",
        "BinarioPartenza": "Bina8",
        "BinarioArrivo": "Bina8",
        "Valuta": "Valu8",
        "PrezzoBase": 268829886.335,
        "Note": "Note8",
        "CreatedBy": "CreatedBy8",
        "CreatedAt": "/Date(780909681000)/",
        "ModifiedBy": "ModifiedBy8",
        "ModifiedAt": "/Date(659707529000)/"
    },
    {
        "NumeroTreno": "uvnTQnPeZk",
        "StazionePartenza": "StazionePartenza9",
        "StazioneArrivo": "StazioneArrivo9",
        "DataPartenza": "/Date(450718789000)/",
        "OraPartenza": "PT10H30M17S",
        "DataArrivo": "/Date(1104676944000)/",
        "OraArrivo": "PT05H02M46S",
        "NumeroMaxPasseggeri": 1214304840,
        "NumeroMinPasseggeri": 1593454696,
        "TipoTreno": "TipoTreno9",
        "StatoTreno": "StatoTreno9",
        "BinarioPartenza": "Bina9",
        "BinarioArrivo": "Bina9",
        "Valuta": "Valu9",
        "PrezzoBase": 9618216268.718,
        "Note": "Note9",
        "CreatedBy": "CreatedBy9",
        "CreatedAt": "/Date(836418995000)/",
        "ModifiedBy": "ModifiedBy9",
        "ModifiedAt": "/Date(1107565290000)/"
    },
    {
        "NumeroTreno": "brCBHPqtVF",
        "StazionePartenza": "StazionePartenza10",
        "StazioneArrivo": "StazioneArrivo10",
        "DataPartenza": "/Date(172715179000)/",
        "OraPartenza": "PT17H33M05S",
        "DataArrivo": "/Date(269914668000)/",
        "OraArrivo": "PT22H48M21S",
        "NumeroMaxPasseggeri": 1224398788,
        "NumeroMinPasseggeri": 159731818,
        "TipoTreno": "TipoTreno10",
        "StatoTreno": "StatoTreno10",
        "BinarioPartenza": "Bin10",
        "BinarioArrivo": "Bin10",
        "Valuta": "Val10",
        "PrezzoBase": 6400211008.731,
        "Note": "Note10",
        "CreatedBy": "CreatedBy10",
        "CreatedAt": "/Date(741298280000)/",
        "ModifiedBy": "ModifiedBy10",
        "ModifiedAt": "/Date(293952537000)/"
    },
    {
        "NumeroTreno": "fjovtBSfbn",
        "StazionePartenza": "StazionePartenza11",
        "StazioneArrivo": "StazioneArrivo11",
        "DataPartenza": "/Date(740227345000)/",
        "OraPartenza": "PT20H22M14S",
        "DataArrivo": "/Date(155264949000)/",
        "OraArrivo": "PT04H38M34S",
        "NumeroMaxPasseggeri": 886775929,
        "NumeroMinPasseggeri": 1018552042,
        "TipoTreno": "TipoTreno11",
        "StatoTreno": "StatoTreno11",
        "BinarioPartenza": "Bin11",
        "BinarioArrivo": "Bin11",
        "Valuta": "Val11",
        "PrezzoBase": 9961591036.99,
        "Note": "Note11",
        "CreatedBy": "CreatedBy11",
        "CreatedAt": "/Date(1202630116000)/",
        "ModifiedBy": "ModifiedBy11",
        "ModifiedAt": "/Date(700383600000)/"
    },
    {
        "NumeroTreno": "tMHFRAgAdF",
        "StazionePartenza": "StazionePartenza12",
        "StazioneArrivo": "StazioneArrivo12",
        "DataPartenza": "/Date(204075599000)/",
        "OraPartenza": "PT16H00M06S",
        "DataArrivo": "/Date(1448908180000)/",
        "OraArrivo": "PT17H12M08S",
        "NumeroMaxPasseggeri": 2134399379,
        "NumeroMinPasseggeri": 763512666,
        "TipoTreno": "TipoTreno12",
        "StatoTreno": "StatoTreno12",
        "BinarioPartenza": "Bin12",
        "BinarioArrivo": "Bin12",
        "Valuta": "Val12",
        "PrezzoBase": 7721264238.934,
        "Note": "Note12",
        "CreatedBy": "CreatedBy12",
        "CreatedAt": "/Date(955590586000)/",
        "ModifiedBy": "ModifiedBy12",
        "ModifiedAt": "/Date(452757296000)/"
    },
    {
        "NumeroTreno": "NYvuGfmJPK",
        "StazionePartenza": "StazionePartenza13",
        "StazioneArrivo": "StazioneArrivo13",
        "DataPartenza": "/Date(1455312154000)/",
        "OraPartenza": "PT17H07M27S",
        "DataArrivo": "/Date(178971158000)/",
        "OraArrivo": "PT21H23M38S",
        "NumeroMaxPasseggeri": 2089081092,
        "NumeroMinPasseggeri": 123896201,
        "TipoTreno": "TipoTreno13",
        "StatoTreno": "StatoTreno13",
        "BinarioPartenza": "Bin13",
        "BinarioArrivo": "Bin13",
        "Valuta": "Val13",
        "PrezzoBase": 1364868171.513,
        "Note": "Note13",
        "CreatedBy": "CreatedBy13",
        "CreatedAt": "/Date(391991102000)/",
        "ModifiedBy": "ModifiedBy13",
        "ModifiedAt": "/Date(465620224000)/"
    },
    {
        "NumeroTreno": "mUJCTCemuf",
        "StazionePartenza": "StazionePartenza14",
        "StazioneArrivo": "StazioneArrivo14",
        "DataPartenza": "/Date(1005723454000)/",
        "OraPartenza": "PT21H10M06S",
        "DataArrivo": "/Date(961582359000)/",
        "OraArrivo": "PT01H55M31S",
        "NumeroMaxPasseggeri": 280208626,
        "NumeroMinPasseggeri": 2068246080,
        "TipoTreno": "TipoTreno14",
        "StatoTreno": "StatoTreno14",
        "BinarioPartenza": "Bin14",
        "BinarioArrivo": "Bin14",
        "Valuta": "Val14",
        "PrezzoBase": 6286344998.516,
        "Note": "Note14",
        "CreatedBy": "CreatedBy14",
        "CreatedAt": "/Date(313416043000)/",
        "ModifiedBy": "ModifiedBy14",
        "ModifiedAt": "/Date(6813659000)/"
    },
    {
        "NumeroTreno": "lPUKnxYKJH",
        "StazionePartenza": "StazionePartenza15",
        "StazioneArrivo": "StazioneArrivo15",
        "DataPartenza": "/Date(46353349000)/",
        "OraPartenza": "PT20H21M13S",
        "DataArrivo": "/Date(398322294000)/",
        "OraArrivo": "PT21H00M47S",
        "NumeroMaxPasseggeri": 1364575754,
        "NumeroMinPasseggeri": 1014074334,
        "TipoTreno": "TipoTreno15",
        "StatoTreno": "StatoTreno15",
        "BinarioPartenza": "Bin15",
        "BinarioArrivo": "Bin15",
        "Valuta": "Val15",
        "PrezzoBase": 2532478296.197,
        "Note": "Note15",
        "CreatedBy": "CreatedBy15",
        "CreatedAt": "/Date(984866265000)/",
        "ModifiedBy": "ModifiedBy15",
        "ModifiedAt": "/Date(571477835000)/"
    },
    {
        "NumeroTreno": "kEUUwGGEig",
        "StazionePartenza": "StazionePartenza16",
        "StazioneArrivo": "StazioneArrivo16",
        "DataPartenza": "/Date(1329119438000)/",
        "OraPartenza": "PT07H10M52S",
        "DataArrivo": "/Date(1343079968000)/",
        "OraArrivo": "PT13H57M50S",
        "NumeroMaxPasseggeri": 414232335,
        "NumeroMinPasseggeri": 2050841190,
        "TipoTreno": "TipoTreno16",
        "StatoTreno": "StatoTreno16",
        "BinarioPartenza": "Bin16",
        "BinarioArrivo": "Bin16",
        "Valuta": "Val16",
        "PrezzoBase": 9287880130.577,
        "Note": "Note16",
        "CreatedBy": "CreatedBy16",
        "CreatedAt": "/Date(863974728000)/",
        "ModifiedBy": "ModifiedBy16",
        "ModifiedAt": "/Date(1460762434000)/"
    },
    {
        "NumeroTreno": "NcTiYYrcNN",
        "StazionePartenza": "StazionePartenza17",
        "StazioneArrivo": "StazioneArrivo17",
        "DataPartenza": "/Date(642285896000)/",
        "OraPartenza": "PT02H30M58S",
        "DataArrivo": "/Date(1165202978000)/",
        "OraArrivo": "PT21H38M00S",
        "NumeroMaxPasseggeri": 633948135,
        "NumeroMinPasseggeri": 13687507,
        "TipoTreno": "TipoTreno17",
        "StatoTreno": "StatoTreno17",
        "BinarioPartenza": "Bin17",
        "BinarioArrivo": "Bin17",
        "Valuta": "Val17",
        "PrezzoBase": 2260105786.845,
        "Note": "Note17",
        "CreatedBy": "CreatedBy17",
        "CreatedAt": "/Date(713000010000)/",
        "ModifiedBy": "ModifiedBy17",
        "ModifiedAt": "/Date(140535277000)/"
    },
    {
        "NumeroTreno": "sZSFNjGiQu",
        "StazionePartenza": "StazionePartenza18",
        "StazioneArrivo": "StazioneArrivo18",
        "DataPartenza": "/Date(956998435000)/",
        "OraPartenza": "PT09H19M00S",
        "DataArrivo": "/Date(1159930845000)/",
        "OraArrivo": "PT01H42M57S",
        "NumeroMaxPasseggeri": 1019724439,
        "NumeroMinPasseggeri": 1264658314,
        "TipoTreno": "TipoTreno18",
        "StatoTreno": "StatoTreno18",
        "BinarioPartenza": "Bin18",
        "BinarioArrivo": "Bin18",
        "Valuta": "Val18",
        "PrezzoBase": 8594128775.876,
        "Note": "Note18",
        "CreatedBy": "CreatedBy18",
        "CreatedAt": "/Date(1198759757000)/",
        "ModifiedBy": "ModifiedBy18",
        "ModifiedAt": "/Date(1294988848000)/"
    },
    {
        "NumeroTreno": "RQEoskJklJ",
        "StazionePartenza": "StazionePartenza19",
        "StazioneArrivo": "StazioneArrivo19",
        "DataPartenza": "/Date(659401616000)/",
        "OraPartenza": "PT13H22M41S",
        "DataArrivo": "/Date(1335485704000)/",
        "OraArrivo": "PT20H48M08S",
        "NumeroMaxPasseggeri": 1130282057,
        "NumeroMinPasseggeri": 1435849998,
        "TipoTreno": "TipoTreno19",
        "StatoTreno": "StatoTreno19",
        "BinarioPartenza": "Bin19",
        "BinarioArrivo": "Bin19",
        "Valuta": "Val19",
        "PrezzoBase": 6211360136.512,
        "Note": "Note19",
        "CreatedBy": "CreatedBy19",
        "CreatedAt": "/Date(1326875936000)/",
        "ModifiedBy": "ModifiedBy19",
        "ModifiedAt": "/Date(1330935691000)/"
    },
    {
        "NumeroTreno": "jdPBWQuJuZ",
        "StazionePartenza": "StazionePartenza20",
        "StazioneArrivo": "StazioneArrivo20",
        "DataPartenza": "/Date(932569858000)/",
        "OraPartenza": "PT13H52M08S",
        "DataArrivo": "/Date(633252412000)/",
        "OraArrivo": "PT11H07M19S",
        "NumeroMaxPasseggeri": 1916308687,
        "NumeroMinPasseggeri": 1993609561,
        "TipoTreno": "TipoTreno20",
        "StatoTreno": "StatoTreno20",
        "BinarioPartenza": "Bin20",
        "BinarioArrivo": "Bin20",
        "Valuta": "Val20",
        "PrezzoBase": 556716653.518,
        "Note": "Note20",
        "CreatedBy": "CreatedBy20",
        "CreatedAt": "/Date(373456112000)/",
        "ModifiedBy": "ModifiedBy20",
        "ModifiedAt": "/Date(1055146470000)/"
    }
]